tests/__init__.py
tests/test.py
tsitools/__init__.py
tsitools/test.py
tsitools-0.1.1.dist-info/LICENSE
tsitools-0.1.1.dist-info/METADATA
tsitools-0.1.1.dist-info/WHEEL
tsitools-0.1.1.dist-info/top_level.txt
tsitools-0.1.1.dist-info/RECORD
