Metadata-Version: 2.1
Name: tsitools
Version: 0.1.1
Summary: A Python module for parsing and analyzing output files from the TSI 3330 optical particle sizer.
Home-page: https://github.com/tayebcodes/tsitools
Author: Tayeb Kakeshpour
Author-email: tayeb.codes@gmail.com
License: MIT
Classifier: Programming Language :: Python :: 3
Classifier: License :: OSI Approved :: MIT License
Classifier: Operating System :: OS Independent
Requires-Python: >=3.9
License-File: LICENSE
Requires-Dist: numpy
Requires-Dist: pandas
